skippy/__init__.py
skippy/__main__.py
skippy/app.py
skippy/config.py
skippy/api/__init__.py
skippy/api/decorators.py
skippy/api/metaclass.py
skippy/api/types.py
skippy/core/__init__.py
skippy/core/autoupdate.py
skippy/core/elements.py
skippy/core/fields.py
skippy/core/plugins.py
skippy/core/preview.py
skippy/core/scpclient.py
skippy/gui/__init__.py
skippy/gui/actionbar.py
skippy/gui/components.py
skippy/gui/editor.py
skippy/gui/loginstatus.py
skippy/gui/mainwindow.py
skippy/gui/resources.py
skippy/gui/settings.py
skippy/gui/sitebox.py
skippy/gui/startui.py
skippy/gui/styles.py
skippy/gui/tabwidget.py
skippy/gui/thread.py
skippy/gui/utils.py
skippy/gui/workers.py
skippy/gui/dialogs/__init__.py
skippy/gui/dialogs/criticalmessage.py
skippy/gui/dialogs/download.py
skippy/gui/dialogs/elements.py
skippy/gui/dialogs/filesdialog.py
skippy/gui/dialogs/finder.py
skippy/gui/dialogs/login.py
skippy/gui/dialogs/plugin.py
skippy/gui/dialogs/previewer.py
skippy/gui/dialogs/updater.py
skippy/gui/dialogs/upload.py
skippy/lang/en.toml
skippy/lang/ja.toml
skippy/lang/ko.toml
skippy/lang/ru.toml
skippy/plugins/example_plugin.py
skippy/resources/skippy.ico
skippy/resources/dark/close.png
skippy/resources/dark/copy.png
skippy/resources/dark/cut.png
skippy/resources/dark/exit.png
skippy/resources/dark/find.png
skippy/resources/dark/load_files.png
skippy/resources/dark/load_session.png
skippy/resources/dark/login.png
skippy/resources/dark/logout.png
skippy/resources/dark/new.png
skippy/resources/dark/open.png
skippy/resources/dark/paste.png
skippy/resources/dark/preview.png
skippy/resources/dark/redo.png
skippy/resources/dark/save_session.png
skippy/resources/dark/select_all.png
skippy/resources/dark/toggle.png
skippy/resources/dark/undo.png
skippy/resources/dark/upload.png
skippy/resources/dark/upload_as.png
skippy/resources/light/close.png
skippy/resources/light/copy.png
skippy/resources/light/cut.png
skippy/resources/light/exit.png
skippy/resources/light/find.png
skippy_pad-1.2.7.dist-info/LICENSE
skippy_pad-1.2.7.dist-info/METADATA
skippy_pad-1.2.7.dist-info/WHEEL
skippy_pad-1.2.7.dist-info/entry_points.txt
skippy_pad-1.2.7.dist-info/top_level.txt
skippy_pad-1.2.7.dist-info/RECORD
