Metadata-Version: 2.1
Name: skippy-pad
Version: 1.2.7
Summary: Simple. Comfortable. Powerful. notepad for www.scpwiki.com.
Home-page: https://github.com/skippy-dev/skippy/
Author: MrNereof
Author-email: mrnereof@gmail.com
License: GPLv3
Keywords: scp,wikidot,pyscp,skippy
Platform: UNKNOWN
Classifier: Development Status :: 3 - Alpha
Classifier: Intended Audience :: Other Audience
Classifier: License :: OSI Approved :: GNU General Public License v3 (GPLv3)
Classifier: Operating System :: OS Independent
Classifier: Programming Language :: Python :: 3.7
Classifier: Programming Language :: Python :: 3.8
Classifier: Programming Language :: Python :: 3.9
Requires-Python: >=3.7
Requires-Dist: pypresence (==4.2.0)
Requires-Dist: requests (==2.25.1)
Requires-Dist: prettytable (==2.0.0)
Requires-Dist: pyscp (==1.1.19)
Requires-Dist: PyQt5 (==5.15.5)
Requires-Dist: toml (==0.10.2)
Provides-Extra: ftml
Requires-Dist: PyQtWebEngine (==5.15.5) ; extra == 'ftml'
Requires-Dist: pyftml (==0.1.2) ; extra == 'ftml'
Provides-Extra: preview
Requires-Dist: PyQtWebEngine (==5.15.5) ; extra == 'preview'
